video_doc_generator/__init__.py
video_doc_generator/cli.py
video_doc_generator/config.py
video_doc_generator/generator.py
video_doc_generator/manager.py
video_doc_generator/models.py
video_doc_generator/parser.py
video_doc_generator/parser_provider.py
video_doc_generator/providers/__init__.py
video_doc_generator/providers/bigpt.py
video_doc_generator-0.1.2.dist-info/licenses/LICENSE
video_doc_generator-0.1.2.dist-info/METADATA
video_doc_generator-0.1.2.dist-info/WHEEL
video_doc_generator-0.1.2.dist-info/entry_points.txt
video_doc_generator-0.1.2.dist-info/top_level.txt
video_doc_generator-0.1.2.dist-info/RECORD
