Metadata-Version: 2.4
Name: video-doc-generator
Version: 0.1.2
Summary: A Python package that manages video links, calls video parsing APIs to read and parse videos, and converts video content into professional documents and analysis reports.
Author-email: Auto Project <ocarina1024@gmail.com>
License-Expression: MIT
Project-URL: Homepage, https://github.com/flashpoint493/video-doc-generator
Project-URL: Documentation, https://github.com/flashpoint493/video-doc-generator#readme
Project-URL: Repository, https://github.com/flashpoint493/video-doc-generator
Project-URL: Issues, https://github.com/flashpoint493/video-doc-generator/issues
Keywords: video,document,parser,api,analysis,converter
Classifier: Development Status :: 3 - Alpha
Classifier: Intended Audience :: Developers
Classifier: Programming Language :: Python :: 3
Classifier: Programming Language :: Python :: 3.8
Classifier: Programming Language :: Python :: 3.9
Classifier: Programming Language :: Python :: 3.10
Classifier: Programming Language :: Python :: 3.11
Classifier: Programming Language :: Python :: 3.12
Requires-Python: >=3.8
License-File: LICENSE
Requires-Dist: requests>=2.31.0
Requires-Dist: pydantic>=2.0.0
Requires-Dist: click>=8.0.0
Requires-Dist: python-dotenv>=1.0.0
Requires-Dist: aiohttp>=3.9.0
Provides-Extra: dev
Requires-Dist: pytest>=7.0; extra == "dev"
Requires-Dist: pytest-cov>=4.0; extra == "dev"
Requires-Dist: ruff>=0.6.0; extra == "dev"
Requires-Dist: mypy>=1.0; extra == "dev"
Requires-Dist: pre-commit>=3.0; extra == "dev"
Dynamic: license-file
